gff3/__init__.py
gff3/gff3.py
gff3-1.0.0.dist-info/AUTHORS.rst
gff3-1.0.0.dist-info/LICENSE
gff3-1.0.0.dist-info/METADATA
gff3-1.0.0.dist-info/WHEEL
gff3-1.0.0.dist-info/top_level.txt
gff3-1.0.0.dist-info/RECORD
