Metadata-Version: 2.1
Name: gff3
Version: 1.0.0
Summary: Manipulate genomic features and validate the syntax and reference sequence of your GFF3 files.
Home-page: https://github.com/hotdogee/gff3-py
Author: Han Lin
Author-email: hotdogee@gmail.com
License: BSD
Keywords: gff3
Platform: UNKNOWN
Classifier: Development Status :: 2 - Pre-Alpha
Classifier: Intended Audience :: Developers
Classifier: License :: OSI Approved :: BSD License
Classifier: Natural Language :: English
Classifier: Programming Language :: Python :: 2
Classifier: Programming Language :: Python :: 2.6
Classifier: Programming Language :: Python :: 2.7
Classifier: Programming Language :: Python :: 3
Classifier: Programming Language :: Python :: 3.3
Classifier: Programming Language :: Python :: 3.4
License-File: LICENSE
License-File: AUTHORS.rst
